bridgeql/__init__.py
bridgeql/types.py
bridgeql/utils.py
bridgeql/django/__init__.py
bridgeql/django/auth.py
bridgeql/django/bridge.py
bridgeql/django/exceptions.py
bridgeql/django/fields.py
bridgeql/django/helpers.py
bridgeql/django/models.py
bridgeql/django/query.py
bridgeql/django/schema.py
bridgeql/django/settings.py
bridgeql/django/urls.py
bridgeql/django/views.py
bridgeql/templates/bridgeql/index.html
bridgeql/templates/bridgeql/schema.html
bridgeql-0.2.2.dist-info/LICENSE
bridgeql-0.2.2.dist-info/METADATA
bridgeql-0.2.2.dist-info/NOTICE
bridgeql-0.2.2.dist-info/WHEEL
bridgeql-0.2.2.dist-info/top_level.txt
bridgeql-0.2.2.dist-info/RECORD
