Metadata-Version: 2.1
Name: bridgeql
Version: 0.2.2
Summary: Query language to bridge the gap between REST API and ORM capability
Home-page: https://github.com/vmware/bridgeql
Author: Piyus Kumar
Author-email: piyusk@vmware.com
License: BSD-2
Project-URL: Bug Tracker, https://github.com/vmware/bridgeql/issues
Keywords: django
Platform: Any
Classifier: Framework :: Django
Classifier: Development Status :: 4 - Beta
Classifier: Programming Language :: Python :: 2.7
Classifier: Intended Audience :: Developers
Classifier: Framework :: Django :: 3.2
Classifier: Programming Language :: Python :: 3.9
Classifier: Framework :: Django :: 1.11
Classifier: Topic :: Software Development :: Libraries :: Python Modules
Classifier: Framework :: Django :: 4.1
Classifier: Programming Language :: Python
Classifier: Operating System :: OS Independent
Classifier: Natural Language :: English
Classifier: License :: OSI Approved :: BSD License
Classifier: Programming Language :: Python :: 3.7
Classifier: Programming Language :: Python :: 3.8
Classifier: Framework :: Django :: 2.2
Requires-Python: >=2.7
License-File: LICENSE
License-File: NOTICE
